pyproject_scaffold/__init__.py
pyproject_scaffold/__main__.py
pyproject_scaffold/main.py
pyproject_scaffold/static/pyproject.toml
pyproject_scaffold-0.1.3.dist-info/LICENSE
pyproject_scaffold-0.1.3.dist-info/METADATA
pyproject_scaffold-0.1.3.dist-info/WHEEL
pyproject_scaffold-0.1.3.dist-info/entry_points.txt
pyproject_scaffold-0.1.3.dist-info/top_level.txt
pyproject_scaffold-0.1.3.dist-info/RECORD
