Metadata-Version: 2.1
Name: pyproject-scaffold
Version: 0.1.3
License-File: LICENSE
Requires-Dist: tomli ==2.0.1
Requires-Dist: tomli-w ==1.0.0
Provides-Extra: dev
Requires-Dist: pytest ; extra == 'dev'
Requires-Dist: pytest-mock ; extra == 'dev'
Requires-Dist: pyfakefs ; extra == 'dev'
